any_parser/__init__.py
any_parser/any_parser.py
any_parser/async_parser.py
any_parser/base_parser.py
any_parser/batch_parser.py
any_parser/constants.py
any_parser/sync_parser.py
any_parser/utils.py
any_parser-0.0.26.dist-info/METADATA
any_parser-0.0.26.dist-info/WHEEL
any_parser-0.0.26.dist-info/RECORD
