Metadata-Version: 2.1
Name: any-parser
Version: 0.0.26
Summary: Parser for all.
Author: CambioML
Author-email: wanwanaiai45@gmail.com
Maintainer: Rachel Hu
Maintainer-email: goldpiggy@berkeley.edu
Requires-Python: >=3.9,<3.13
Classifier: Programming Language :: Python :: 3
Classifier: Programming Language :: Python :: 3.9
Classifier: Programming Language :: Python :: 3.10
Classifier: Programming Language :: Python :: 3.11
Requires-Dist: pydantic (>=2.10.3,<3.0.0)
Requires-Dist: python-dotenv (>=1.0.0,<2.0.0)
Requires-Dist: requests (>=2.25.0,<3.0.0)
